storable/__init__.py
storable/core.py
storable/output.py
storable-1.2.4.dist-info/LICENSE.txt
storable-1.2.4.dist-info/METADATA
storable-1.2.4.dist-info/WHEEL
storable-1.2.4.dist-info/top_level.txt
storable-1.2.4.dist-info/RECORD
