Metadata-Version: 2.1
Name: storable
Version: 1.2.4
Summary: Python Perl Storable module
Home-page: http://github.com/CowboyTim/python-storable
Author: CowboyTim
Author-email: aardbeiplantje@gmail.com
License: zlib/libpng
Platform: UNKNOWN
Classifier: Development Status :: 3 - Alpha
Classifier: Intended Audience :: Developers
Classifier: Programming Language :: Perl
Classifier: Programming Language :: Python :: 2
Classifier: Programming Language :: Python :: 3
Classifier: License :: OSI Approved :: zlib/libpng License
Provides-Extra: test
License-File: LICENSE.txt
